mcp_gsuite/__init__.py
mcp_gsuite/auth_helper.py
mcp_gsuite/calendar.py
mcp_gsuite/calendar_tools.py
mcp_gsuite/common.py
mcp_gsuite/drive.py
mcp_gsuite/drive_tools.py
mcp_gsuite/fast_server.py
mcp_gsuite/gauth.py
mcp_gsuite/gmail.py
mcp_gsuite/gmail_drive_tools.py
mcp_gsuite/gmail_tools.py
mcp_gsuite/settings.py
mcp_gsuite/setup_cli.py
fastmcp_gsuite-1.1.0.dist-info/METADATA
fastmcp_gsuite-1.1.0.dist-info/WHEEL
fastmcp_gsuite-1.1.0.dist-info/entry_points.txt
fastmcp_gsuite-1.1.0.dist-info/licenses/LICENSE
fastmcp_gsuite-1.1.0.dist-info/RECORD
