Metadata-Version: 2.4
Name: fastmcp-gsuite
Version: 1.1.0
Summary: MCP Server to connect to Google G-Suite
Author-email: tumf <tumf@users.noreply.github.com>
License-File: LICENSE
Requires-Python: >=3.13
Requires-Dist: beautifulsoup4>=4.12.3
Requires-Dist: detect-secrets>=1.5.0
Requires-Dist: fastmcp<2.2.0,>=2.1.2
Requires-Dist: google-api-python-client>=2.154.0
Requires-Dist: httplib2>=0.22.0
Requires-Dist: oauth2client==4.1.3
Requires-Dist: pydantic-settings<2.9.0,>=2.8.1
Requires-Dist: python-dotenv>=1.0.1
Requires-Dist: pytz>=2024.2
Requires-Dist: requests>=2.32.3
Requires-Dist: types-httplib2>=0.22.0.20250401
Requires-Dist: types-pytz>=2025.2.0.20250326
Provides-Extra: dev
Requires-Dist: pyright>=1.1.389; extra == 'dev'
Provides-Extra: e2e
Requires-Dist: google-api-python-client>=2.154.0; extra == 'e2e'
Requires-Dist: google-auth-httplib2>=0.1.1; extra == 'e2e'
Requires-Dist: google-auth-oauthlib>=1.2.1; extra == 'e2e'
Requires-Dist: google-auth>=2.27.0; extra == 'e2e'
Requires-Dist: pytest>=8.3.5; extra == 'e2e'
